Metadata-Version: 1.1
Name: libqrencode-ctypes
Version: 0.1.0
Summary: Python ctypes libqrencode wrapper
Home-page: https://github.com/zaazbb/libqrencode-ctypes
Author: zaazbb
Author-email: zaazbb@163.com
License: LGPL
Keywords: libqrencode ctypes
Platform: UNKNOWN
Classifier: Development Status :: 3 - Alpha
Classifier: Topic :: Software Development :: Libraries :: Python Modules
Classifier: License :: Freeware
Classifier: Programming Language :: Python :: 3
Classifier: Programming Language :: Python :: 3.4
Classifier: Programming Language :: Python :: 3.5
Classifier: Programming Language :: Python :: 3.6
Classifier: Operating System :: POSIX :: Linux
